simple_parquet_viewer/__init__.py
simple_parquet_viewer/main.py
simple_parquet_viewer/res/imgs/app_icon.ico
simple_parquet_viewer/res/imgs/app_icon.svg
simple_parquet_viewer/res/imgs/apply.png
simple_parquet_viewer/res/imgs/apply.svg
simple_parquet_viewer/res/imgs/clear.png
simple_parquet_viewer/res/imgs/clear.svg
simple_parquet_viewer/res/imgs/filter.png
simple_parquet_viewer/res/imgs/filter.svg
simple_parquet_viewer/res/imgs/info.png
simple_parquet_viewer/res/imgs/info.svg
simple_parquet_viewer/res/imgs/info_qt.png
simple_parquet_viewer/res/imgs/info_qt.svg
simple_parquet_viewer/res/imgs/open.png
simple_parquet_viewer/res/imgs/open.svg
simple_parquet_viewer/res/imgs/save_csv.png
simple_parquet_viewer/res/imgs/save_csv.svg
simple_parquet_viewer/res/imgs/save_json.png
simple_parquet_viewer/res/imgs/save_json.svg
simple_parquet_viewer/res/imgs/save_parquet.png
simple_parquet_viewer/res/imgs/save_parquet.svg
simple_parquet_viewer/res/imgs/save_xlsx.png
simple_parquet_viewer/res/imgs/save_xlsx.svg
simple_parquet_viewer/res/stylesheet/dark.css
simple_parquet_viewer/res/translations/pt.qm
simple_parquet_viewer/res/translations/pt.ts
simple_parquet_viewer/widgets/mainwindow.py
simple_parquet_viewer-0.11.1.dist-info/METADATA
simple_parquet_viewer-0.11.1.dist-info/WHEEL
simple_parquet_viewer-0.11.1.dist-info/entry_points.txt
simple_parquet_viewer-0.11.1.dist-info/licenses/LICENCE.txt
simple_parquet_viewer-0.11.1.dist-info/RECORD
