Metadata-Version: 2.1
Name: simple-parquet-viewer
Version: 0.11.1
Summary: A simple (and lightweight) visualization tool for Parquet files.
Project-URL: Homepage, https://github.com/mauromascarenhas/simple-parquet-viewer
Project-URL: Bug Tracker, https://github.com/mauromascarenhas/simple-parquet-viewer/issues
Author-email: Mauro Mascarenhas de Araújo <mauromascarenhas@users.noreply.github.com>
License-Expression: GPL-3.0-or-later
License-File: LICENCE.txt
Keywords: GUI,Parquet,Viewer
Classifier: License :: OSI Approved :: GNU General Public License v3 or later (GPLv3+)
Classifier: Operating System :: OS Independent
Classifier: Programming Language :: Python :: 3
Requires-Python: >=3.7
Requires-Dist: numpy>=1.24
Requires-Dist: pandas>=2.0
Requires-Dist: pyarrow
Requires-Dist: pyqt6~=6.5
Requires-Dist: xlsxwriter>=3.0
Provides-Extra: windows
Requires-Dist: pywin32>=306; extra == 'windows'
